{"Total": {"AE": 1.0, "AR": 29.0, "AT": 2.0, "AU": 18.0, "BB": 23.0, "BD": 1.0, "BE": 2.0, "BG": 1.0, "BJ": 2.0, "BO": 2.0, "BR": 42.0, "BS": 4.0, "BT": 25.0, "BW": 1.0, "BZ": 1.0, "CA": 45.0, "CH": 47.0, "CI": 1.0, "CL": 29.0, "CM": 1.0, "CN": 743.0, "CO": 36.0, "CR": 13.0, "DE": 23.0, "DK": 3.0, "DO": 3.0, "EC": 41.0, "EG": 1.0, "ES": 44.0, "ET": 8.0, "FR": 21.0, "GB": 175.0, "GE": 2.0, "GH": 2.0, "GR": 1.0, "GT": 3.0, "HU": 2.0, "ID": 15.0, "IL": 3.0, "IN": 65.0, "IT": 23.0, "JM": 1.0, "JO": 1.0, "JP": 6.0, "KE": 43.0, "KG": 2.0, "KH": 34.0, "KR": 32.0, "KZ": 1.0, "LA": 4.0, "LK": 3.0, "LR": 1.0, "LT": 3.0, "MA": 1.0, "MG": 2.0, "MM": 7.0, "MN": 34.0, "MQ": 1.0, "MX": 27.0, "MY": 7.0, "MZ": 91.0, "NG": 3.0, "NI": 7.0, "NL": 6.0, "NO": 6.0, "NP": 3.0, "NZ": 6.0, "PA": 2.0, "PE": 53.0, "PH": 6.0, "PK": 3.0, "PR": 1.0, "PT": 13.0, "RO": 24.0, "RU": 3.0, "SC": 1.0, "SE": 10.0, "SG": 3.0, "SI": 2.0, "SR": 1.0, "SZ": 1.0, "TH": 8.0, "TN": 5.0, "TT": 1.0, "TZ": 2.0, "US": 781.0, "VN": 11.0, "ZA": 23.0, "ZW": 1.0}, "2013": {"MZ": 24.0, "CH": 4.0, "PA": 1.0, "NZ": 3.0, "CL": 24.0, "CM": 1.0, "CN": 3.0, "NL": 1.0, "NI": 7.0, "ID": 3.0, "CO": 5.0, "MY": 2.0, "CR": 2.0, "MX": 6.0, "PE": 44.0, "MN": 20.0, "DK": 2.0, "DO": 3.0, "EC": 4.0, "LA": 1.0, "ES": 30.0, "KH": 24.0, "KG": 1.0, "KE": 1.0, "JP": 1.0, "IT": 2.0, "GB": 143.0, "GE": 2.0, "GT": 2.0, "DE": 5.0, "PH": 1.0, "HU": 1.0, "VN": 5.0, "BG": 1.0, "BR": 9.0, "AU": 6.0, "SG": 1.0, "BE": 1.0, "US": 144.0, "SE": 1.0, "CA": 19.0, "AR": 28.0, "PT": 1.0}, "2014": {"FR": 4.0, "DE": 1.0, "BB": 2.0, "LT": 2.0, "PH": 3.0, "BE": 1.0, "IT": 4.0, "ES": 8.0, "EC": 2.0, "TT": 1.0, "US": 86.0, "VN": 1.0, "KR": 24.0, "KH": 1.0, "BO": 1.0, "CA": 4.0, "JP": 1.0, "GR": 1.0, "NZ": 1.0, "NP": 1.0, "NO": 1.0, "PT": 9.0, "CL": 2.0, "ID": 1.0, "CN": 3.0, "CR": 8.0, "GB": 2.0, "IL": 1.0, "BR": 4.0, "CO": 3.0, "IN": 62.0, "MX": 5.0, "NL": 4.0}, "2015": {"ID": 3.0, "ZA": 18.0, "IL": 1.0, "VN": 3.0, "JO": 1.0, "LK": 1.0, "US": 24.0, "PH": 2.0, "PR": 1.0, "NL": 1.0, "RO": 1.0, "SI": 2.0, "TH": 7.0, "MY": 3.0, "MX": 4.0, "TN": 5.0, "MM": 5.0, "MA": 1.0, "LA": 3.0, "TZ": 1.0, "KZ": 1.0, "KH": 7.0, "KE": 40.0, "AE": 1.0, "IT": 15.0, "ZW": 1.0, "DE": 5.0, "CO": 18.0, "HU": 1.0, "CN": 1.0, "EC": 31.0, "CH": 24.0, "EG": 1.0, "BW": 1.0, "BT": 23.0, "FR": 7.0, "ET": 6.0, "GH": 2.0, "BB": 19.0, "GB": 1.0, "AT": 2.0, "BD": 1.0}, "2016": {"BJ": 2.0, "AU": 4.0, "NZ": 1.0, "CH": 6.0, "NO": 2.0, "VN": 2.0, "AR": 1.0, "MZ": 60.0, "MY": 2.0, "ZA": 3.0, "CO": 3.0, "MX": 8.0, "CN": 12.0, "PA": 1.0, "CA": 6.0, "US": 171.0, "BZ": 1.0, "BT": 2.0, "MQ": 1.0, "PT": 1.0, "RU": 1.0, "BS": 2.0, "SE": 1.0, "BB": 2.0, "SR": 1.0, "SZ": 1.0, "BR": 4.0, "TH": 1.0, "BO": 1.0, "PE": 1.0, "MN": 1.0, "GT": 1.0, "EC": 1.0, "KG": 1.0, "KH": 2.0, "FR": 4.0, "IN": 1.0, "DE": 4.0, "ID": 3.0, "GB": 16.0, "ET": 1.0}, "2017": {"ZA": 1.0, "BS": 2.0, "ES": 3.0, "FR": 3.0, "CA": 10.0, "RO": 22.0, "CR": 1.0, "SG": 1.0, "EC": 2.0, "KR": 4.0, "BR": 2.0, "CO": 4.0, "SE": 6.0, "CH": 5.0, "NP": 2.0, "MG": 2.0, "NO": 3.0, "ID": 2.0, "DE": 5.0, "JP": 1.0, "GB": 7.0, "MZ": 1.0, "AU": 1.0, "MX": 1.0, "NG": 1.0, "CN": 381.0, "LK": 1.0, "US": 185.0, "PT": 2.0, "DK": 1.0, "SC": 1.0, "RU": 1.0}, "2018": {"SG": 1.0, "MN": 13.0, "IT": 2.0, "ZA": 1.0, "FR": 3.0, "IN": 2.0, "TZ": 1.0, "IL": 1.0, "AU": 7.0, "US": 171.0, "ID": 3.0, "GB": 6.0, "JM": 1.0, "BR": 23.0, "ES": 3.0, "ET": 1.0, "MM": 2.0, "CO": 3.0, "MX": 3.0, "LT": 1.0, "CN": 343.0, "LR": 1.0, "MZ": 6.0, "LK": 1.0, "DE": 3.0, "CL": 3.0, "CI": 1.0, "CH": 8.0, "KR": 4.0, "NZ": 1.0, "CA": 6.0, "PE": 8.0, "EC": 1.0, "PK": 3.0, "CR": 2.0, "KE": 2.0, "RO": 1.0, "JP": 3.0, "RU": 1.0, "SE": 2.0, "NG": 2.0}}